pyniki/__init__.py
pyniki/curses.py
pyniki/field.py
pyniki/main.py
pyniki/sim.py
pyniki/ui.py
pyniki-0.0.6.dist-info/METADATA
pyniki-0.0.6.dist-info/WHEEL
pyniki-0.0.6.dist-info/entry_points.txt
pyniki-0.0.6.dist-info/licenses/LICENSE
pyniki-0.0.6.dist-info/RECORD
