Metadata-Version: 2.1
Name: pyNIKI
Version: 0.0.6
Summary: Classic Niki the robot in Python
Project-URL: Homepage, https://github.com/sdrave/pyniki
Author-email: Stephan Rave <stephan.rave@uni-muenster.de>
Maintainer-email: Stephan Rave <stephan.rave@uni-muenster.de>
License:                     GNU GENERAL PUBLIC LICENSE
License-File: LICENSE
Classifier: Development Status :: 2 - Pre-Alpha
Classifier: Intended Audience :: Science/Research
Classifier: License :: OSI Approved :: GNU General Public License v2 (GPLv2)
Classifier: Programming Language :: Python :: 3.8
Classifier: Programming Language :: Python :: 3.9
Classifier: Programming Language :: Python :: 3.10
Classifier: Programming Language :: Python :: 3.11
Classifier: Topic :: Education
Requires-Python: >=3.8
